super_progress_bar/__init__.py
super_progress_bar-0.1.0.dist-info/METADATA
super_progress_bar-0.1.0.dist-info/WHEEL
super_progress_bar-0.1.0.dist-info/top_level.txt
super_progress_bar-0.1.0.dist-info/RECORD
