Metadata-Version: 2.4
Name: super_progress_bar
Version: 0.1.0
Summary: A colorful terminal progress bar with ETA and speed display
Author-email: Davi Luiz Carneiro da Cunha <daviluizradical10@gmail.com>
License: MIT
Requires-Python: >=3.6
